README.txt
TODO.txt
setup.py
collective/__init__.py
collective.megaphonecicerolookup.egg-info/PKG-INFO
collective.megaphonecicerolookup.egg-info/SOURCES.txt
collective.megaphonecicerolookup.egg-info/dependency_links.txt
collective.megaphonecicerolookup.egg-info/entry_points.txt
collective.megaphonecicerolookup.egg-info/namespace_packages.txt
collective.megaphonecicerolookup.egg-info/not-zip-safe
collective.megaphonecicerolookup.egg-info/requires.txt
collective.megaphonecicerolookup.egg-info/top_level.txt
collective/megaphonecicerolookup/__init__.py
collective/megaphonecicerolookup/address_lookup.py
collective/megaphonecicerolookup/configure.zcml
collective/megaphonecicerolookup/events.py
collective/megaphonecicerolookup/form_snippet.pt
collective/megaphonecicerolookup/interfaces.py
collective/megaphonecicerolookup/profiles/default/metadata.xml
collective/megaphonecicerolookup/profiles/default/registry.xml
collective/megaphonecicerolookup/tests/__init__.py
collective/megaphonecicerolookup/tests/base.py
collective/megaphonecicerolookup/tests/layer.py
collective/megaphonecicerolookup/tests/test_lookup.py
docs/HISTORY.txt