Metadata-Version: 1.0
Name: collective.megaphonecicerolookup
Version: 1.0
Summary: Megaphone plugin to look up elected officials based on address, via the Cicero API
Home-page: http://svn.plone.org/svn/collective/collective.megaphonecicerolookup/trunk
Author: David Glick, Groundwire
Author-email: davidglick@groundwire.org
License: GPL
Keywords: megaphone petition letter plone legislator official geocoding
Platform: UNKNOWN
Classifier: Programming Language :: Python
